PoreFinder/__init__.py
PoreFinder/download_files.py
PoreFinder/hole_analysis.py
PoreFinder/porefinder.py
PoreFinder/visualization.py
PoreFinder/ProbeParticleEllipsoid/ellipse_lib.py
PoreFinder/ProbeParticleEllipsoid/ellipsoid_optimisation.py
PoreFinder/hole2/hole
PoreFinder/hole2/sos_triangle
PoreFinder/hole2/sph_process
PoreFinder/pdb_models/7tu9.pdb
PoreFinder/pdb_models/7tu9.pdb_ellipsoid.pdb
PoreFinder/pdb_models/7tu9_aligned_z.pdb
PoreFinder/pdb_models/7tu9_aligned_z.pdb100.pdb
PoreFinder/pdb_models/7tu9_aligned_z.pdb11.pdb
PoreFinder/pdb_models/7tu9_aligned_z.pdb12.pdb
PoreFinder/pdb_models/7tu9_aligned_z.pdb13.pdb
PoreFinder/pdb_models/7tu9_aligned_z.pdb14.pdb
PoreFinder/pdb_models/7tu9_aligned_z.pdb24.pdb
PoreFinder/pdb_models/7tu9_aligned_z.pdb37.pdb
PoreFinder/pdb_models/7tu9_aligned_z.pdb6.pdb
PoreFinder/pdb_models/7tu9_aligned_z.pdb8.pdb
PoreFinder/pdb_models/7tu9_aligned_z.pdb80.pdb
PoreFinder/pdb_models/7tu9_aligned_z.pdb9.pdb
PoreFinder/pdb_models/7tu9_aligned_z.pdb_ellipsoid.pdb
PoreFinder/pdb_models/7tu9a_aligned_z.pdb
PoreFinder/pdb_models/7tvi.pdb
PoreFinder/pdb_models/8fe1.pdb
PoreFinder/pdb_models/8fe1_aligned_z.pdb
PoreFinder/pdb_models/8fe1_aligned_z.pdb100.pdb
PoreFinder/pdb_models/8fe1_aligned_z.pdb_ellipsoid.pdb
PoreFinder/pdb_models/8fe1_aligned_z.s
PoreFinder/pdb_models/8fe1_aligned_z_aligned_z.pdb
PoreFinder/tests/__init__.py
PoreFinder/tests/test_ellipse.py
PoreFinder/tests/test_ellipsoid_optimisation.py
PoreFinder/tests/test_hole.py
PoreFinder/tests/test_visualization.py
porefinder-0.0.3.dist-info/entry_points.txt
porefinder-0.0.3.dist-info/LICENSE
porefinder-0.0.3.dist-info/WHEEL
porefinder-0.0.3.dist-info/METADATA
porefinder-0.0.3.dist-info/RECORD
